fbparser/__init__.py
fbparser/fbparser.py
fbparser-1.0.0.dist-info/DESCRIPTION.rst
fbparser-1.0.0.dist-info/METADATA
fbparser-1.0.0.dist-info/RECORD
fbparser-1.0.0.dist-info/WHEEL
fbparser-1.0.0.dist-info/entry_points.txt
fbparser-1.0.0.dist-info/metadata.json
fbparser-1.0.0.dist-info/top_level.txt
