Metadata-Version: 2.0
Name: fbparser
Version: 1.0.0
Summary: Library/CLI utility to parse, organize and export messages in Facebook archives
Home-page: https://github.com/arcward/fbparser
Author: Edward Wells
Author-email: git@edward.sh
License: MIT
Keywords: facebook fb message messages archive parser parsing export
Platform: UNKNOWN
Classifier: License :: OSI Approved :: MIT License
Classifier: Natural Language :: English
Classifier: Programming Language :: Python :: 3.5
Requires-Dist: python-dateutil (>=2.5.3)
